dsci_524_ezplot/__init__.py
dsci_524_ezplot/plot_heatmap.py
dsci_524_ezplot/plot_histogram.py
dsci_524_ezplot/plot_line.py
dsci_524_ezplot/plot_scatterplot.py
dsci_524_ezplot-0.0.6.dist-info/LICENSE
dsci_524_ezplot-0.0.6.dist-info/METADATA
dsci_524_ezplot-0.0.6.dist-info/WHEEL
dsci_524_ezplot-0.0.6.dist-info/RECORD
