Metadata-Version: 2.3
Name: dsci_524_ezplot
Version: 0.0.6
Summary: A Python package for enhanced data visualization
License: MIT
Author: Daduica Julian, Elshaday Yoseph, Henry(Mu) Ha, Zhou Yining
Requires-Python: >=3.11
Classifier: License :: OSI Approved :: MIT License
Classifier: Programming Language :: Python :: 3
Classifier: Programming Language :: Python :: 3.11
Classifier: Programming Language :: Python :: 3.12
Classifier: Programming Language :: Python :: 3.13
Requires-Dist: matplotlib (>=3.10.0)
Requires-Dist: pandas (>=2.2.3)
Requires-Dist: seaborn (>=0.13.2,<0.14.0)
